<PAMDataset>
  <PAMRasterBand band="1">
    <Histograms>
      <HistItem>
        <HistMin>92.42404174804688</HistMin>
        <HistMax>155.4626770019531</HistMax>
        <BucketCount>256</BucketCount>
        <IncludeOutOfRange>1</IncludeOutOfRange>
        <Approximate>0</Approximate>
        <HistCounts>1|0|0|0|0|0|0|0|0|0|0|0|2|1|0|0|0|2|0|0|1|2|1|1|1|1|1|1|0|1|0|1|1|0|0|1|2|2|0|1|2|0|0|2|2|2|1|6|1|4|2|1|2|0|2|3|4|2|3|4|1|1|4|3|3|5|6|2|1|4|2|6|5|5|2|9|1|2|1|8|4|6|5|1|4|2|6|2|5|9|1|10|3|3|4|2|5|3|3|4|3|14|3|6|5|7|5|6|9|6|8|8|8|5|7|9|9|5|4|6|12|14|8|8|8|10|7|9|9|9|9|9|8|8|12|12|7|14|7|12|6|9|6|10|13|7|8|11|4|13|10|6|15|8|12|8|8|7|10|4|4|9|8|9|5|7|9|6|4|4|8|7|7|8|3|7|6|6|5|8|9|6|5|6|6|8|8|3|0|7|7|1|4|5|4|5|7|5|4|3|2|3|4|5|1|1|0|1|1|3|1|0|2|1|3|2|2|4|3|1|4|1|2|0|3|1|2|0|2|0|1|0|0|1|2|0|0|1|0|1|0|0|3|1|1|0|0|0|0|0|0|0|1|1|1|1</HistCounts>
      </HistItem>
    </Histograms>
    <Metadata>
      <MDI key="RepresentationType">ATHEMATIC</MDI>
      <MDI key="STATISTICS_COVARIANCES">130.5915040297383</MDI>
      <MDI key="STATISTICS_EXCLUDEDVALUES"></MDI>
      <MDI key="STATISTICS_MAXIMUM">155.46267700195</MDI>
      <MDI key="STATISTICS_MEAN">125.76564171307</MDI>
      <MDI key="STATISTICS_MEDIAN">126.044647</MDI>
      <MDI key="STATISTICS_MINIMUM">92.424041748047</MDI>
      <MDI key="STATISTICS_SKIPFACTORX">1</MDI>
      <MDI key="STATISTICS_SKIPFACTORY">1</MDI>
      <MDI key="STATISTICS_STDDEV">11.42766397956</MDI>
    </Metadata>
  </PAMRasterBand>
</PAMDataset>
